pyqt_windows_os_light_dark_theme_window/__init__.py
pyqt_windows_os_light_dark_theme_window/c.py
pyqt_windows_os_light_dark_theme_window/main.py
pyqt_windows_os_light_dark_theme_window-0.0.1.dist-info/LICENSE
pyqt_windows_os_light_dark_theme_window-0.0.1.dist-info/METADATA
pyqt_windows_os_light_dark_theme_window-0.0.1.dist-info/WHEEL
pyqt_windows_os_light_dark_theme_window-0.0.1.dist-info/top_level.txt
pyqt_windows_os_light_dark_theme_window-0.0.1.dist-info/RECORD
